README.rst
setup.py
pyqrcodec/__init__.py
pyqrcodec/bchcode.py
pyqrcodec/bitutil.py
pyqrcodec/galois.py
pyqrcodec/galois_test.py
pyqrcodec/origin.py
pyqrcodec/polynome.py
pyqrcodec/polynome_test.py
pyqrcodec/qrcode.py
pyqrcodec/qrcode_test.py
pyqrcodec/ttt.py
pyqrcodec.egg-info/PKG-INFO
pyqrcodec.egg-info/SOURCES.txt
pyqrcodec.egg-info/dependency_links.txt
pyqrcodec.egg-info/not-zip-safe
pyqrcodec.egg-info/requires.txt
pyqrcodec.egg-info/top_level.txt